bioverse/__init__.py
bioverse/analysis.py
bioverse/classes.py
bioverse/constants.py
bioverse/custom.py
bioverse/functions.py
bioverse/generator.py
bioverse/gui.py
bioverse/hypothesis.py
bioverse/plots.py
bioverse/survey.py
bioverse/truncnorm_hack.py
bioverse/util.py
bioverse/Data/Gaia.csv
bioverse/Data/LUVOIR_targets.dat
bioverse/Data/Pecaut2013.dat
bioverse/Data/avg_deltaR_deltaRho.csv
bioverse/Data/deltaR_DornLichtenberg21_Fig3b.csv
bioverse/Data/gcns_catalog.dat
bioverse/Data/legend.dat
bioverse/Data/mass-radius_relationships_Earthlike_Zeng2016.txt
bioverse/Data/mass-radius_relationships_STEAM_TURBET2020_FIG2b.dat
bioverse/Data/mass-radius_relationships_condensed_Turbet2020_Fig2a.dat
bioverse/Data/mass-radius_relationships_mgsio3_Zeng2016.txt
bioverse/Data/luminosity_tracks/Lum_m0.1.txt
bioverse/Data/luminosity_tracks/Lum_m0.2.txt
bioverse/Data/luminosity_tracks/Lum_m0.4.txt
bioverse/Data/luminosity_tracks/Lum_m0.6.txt
bioverse/Data/luminosity_tracks/Lum_m0.8.txt
bioverse/Data/luminosity_tracks/Lum_m1.0.txt
bioverse/Data/luminosity_tracks/Lum_m1.2.txt
bioverse/Data/luminosity_tracks/Lum_m1.4.txt
bioverse/Objects/Generators/imaging.pkl
bioverse/Objects/Generators/transit.pkl
bioverse/Objects/ImagingSurveys/default.pkl
bioverse/Objects/TransitSurveys/default.pkl
bioverse/UI/generatorWindow.ui
bioverse/UI/priorityDialog.ui
bioverse/UI/startDialog.ui
bioverse/UI/surveyWindow.ui
bioverse-1.1.8.dist-info/licenses/LICENSE
bioverse-1.1.8.dist-info/METADATA
bioverse-1.1.8.dist-info/WHEEL
bioverse-1.1.8.dist-info/top_level.txt
bioverse-1.1.8.dist-info/RECORD
